src/__init__.py
src/svc_monitor.py
src/svc_monitor_prom.py
py_svc_monitor_fcx-0.0.1.dist-info/METADATA
py_svc_monitor_fcx-0.0.1.dist-info/WHEEL
py_svc_monitor_fcx-0.0.1.dist-info/licenses/LICENSE
py_svc_monitor_fcx-0.0.1.dist-info/RECORD
