Metadata-Version: 2.1
Name: py_svc_monitor_fcx
Version: 0.0.1
Summary: Package for adding generic Prometheus (and extensible) monitoring to python services
Project-URL: Homepage, https://github.com/FacilityConneX/py-svc-monitor
Author-email: Nathan Carey <ncarey@facilityconnex.com>
License-File: LICENSE
Classifier: License :: OSI Approved :: MIT License
Classifier: Operating System :: OS Independent
Classifier: Programming Language :: Python :: 3
Requires-Python: >=3.7
